onex/__init__.py
onex/core.py
onex/py.typed
onex/version.py
onex/adapters/__init__.py
onex/adapters/jax_adapter.py
onex/adapters/pytorch_adapter.py
onex/adapters/tensorflow_adapter.py
onex/exporters/__init__.py
onex/exporters/async_exporter.py
onex/utils/__init__.py
onex/utils/assessment_config.py
onex/utils/framework_detector.py
onex_sdk-0.1.28.dist-info/licenses/LICENSE
onex_sdk-0.1.28.dist-info/METADATA
onex_sdk-0.1.28.dist-info/WHEEL
onex_sdk-0.1.28.dist-info/top_level.txt
onex_sdk-0.1.28.dist-info/RECORD
